<?xml version="1.0" encoding="UTF-8" standalone="no"?>
<XML>
    <Flows/>
    <ProcessModules/>
    <FlowValueMapGroups/>
    <ProductSystems/>
    <ImpactCategories>
        <ImpactCategory>
            <Category>Verknappung von abiotischen Ressourcen(Elemente) </Category>
            <Indicator>
                    kg Sb eq.
                </Indicator>
        </ImpactCategory>
        <ImpactCategory>
            <Category>Verknappung von fossiler Ressourcen</Category>
            <Indicator>
                    MJ
                </Indicator>
        </ImpactCategory>
        <ImpactCategory>
            <Category>Versauerung</Category>
            <Indicator>
                    kg SO2 eq.
                </Indicator>
        </ImpactCategory>
        <ImpactCategory>
            <Category>Eutrophierung</Category>
            <Indicator>
                    kg (PO4)3- eq.
                </Indicator>
        </ImpactCategory>
        <ImpactCategory>
            <Category>Klimawandel</Category>
            <Indicator>
                    kg CO2 eq.
                </Indicator>
        </ImpactCategory>
        <ImpactCategory>
            <Category>Abbau der stratosphärischen Ozonschicht</Category>
            <Indicator>
                    kg CFC 11 eq.
                </Indicator>
        </ImpactCategory>
        <ImpactCategory>
            <Category>Bildung von troposphärischen Ozon</Category>
            <Indicator>
                    kg C2H2 eq.
                </Indicator>
        </ImpactCategory>
    </ImpactCategories>
    <CFactors/>
    <LCIAMethods/>
    <ProductDeclarations>
        <ProductDeclaration>
            <PD-Name>Außen- und Innenwandbekleidungen - MN Metall GmbH - Fassadenbekleidungen(de)</PD-Name>
            <PD-Unit>m2</PD-Unit>
            <ImpactValuesVector>
                <IVV-Entry>
                    <ImpactCategorie-Name>Verknappung von abiotischen Ressourcen(Elemente) </ImpactCategorie-Name>
                    <ICV-MainValue>0</ICV-MainValue>
                    <ICV-UpperBound>0</ICV-UpperBound>
                    <ICV-LowerBound>0</ICV-LowerBound>
                </IVV-Entry>
                <IVV-Entry>
                    <ImpactCategorie-Name>Verknappung von fossiler Ressourcen</ImpactCategorie-Name>
                    <ICV-MainValue>1769.8</ICV-MainValue>
                    <ICV-UpperBound>1769.8</ICV-UpperBound>
                    <ICV-LowerBound>1769.8</ICV-LowerBound>
                </IVV-Entry>
                <IVV-Entry>
                    <ImpactCategorie-Name>Versauerung</ImpactCategorie-Name>
                    <ICV-MainValue>0.38</ICV-MainValue>
                    <ICV-UpperBound>0.38</ICV-UpperBound>
                    <ICV-LowerBound>0.38</ICV-LowerBound>
                </IVV-Entry>
                <IVV-Entry>
                    <ImpactCategorie-Name>Eutrophierung</ImpactCategorie-Name>
                    <ICV-MainValue>0.07</ICV-MainValue>
                    <ICV-UpperBound>0.07</ICV-UpperBound>
                    <ICV-LowerBound>0.07</ICV-LowerBound>
                </IVV-Entry>
                <IVV-Entry>
                    <ImpactCategorie-Name>Klimawandel</ImpactCategorie-Name>
                    <ICV-MainValue>180.26</ICV-MainValue>
                    <ICV-UpperBound>180.26</ICV-UpperBound>
                    <ICV-LowerBound>180.26</ICV-LowerBound>
                </IVV-Entry>
                <IVV-Entry>
                    <ImpactCategorie-Name>Abbau der stratosphärischen Ozonschicht</ImpactCategorie-Name>
                    <ICV-MainValue>0</ICV-MainValue>
                    <ICV-UpperBound>0</ICV-UpperBound>
                    <ICV-LowerBound>0</ICV-LowerBound>
                </IVV-Entry>
                <IVV-Entry>
                    <ImpactCategorie-Name>Bildung von troposphärischen Ozon</ImpactCategorie-Name>
                    <ICV-MainValue>0.03</ICV-MainValue>
                    <ICV-UpperBound>0.03</ICV-UpperBound>
                    <ICV-LowerBound>0.03</ICV-LowerBound>
                </IVV-Entry>
            </ImpactValuesVector>
        </ProductDeclaration>
    </ProductDeclarations>
    <ImpactValueMapGroups/>
    <Components>
        <Component>
            <Component-Name>Komponent_Außen- und Innenwandbekleidungen - MN Metall GmbH - Fassadenbekleidungen</Component-Name>
            <Component-Unit>m2</Component-Unit>
            <Component-Reference>Außen- und Innenwandbekleidungen - MN Metall GmbH - Fassadenbekleidungen(de)</Component-Reference>
            <ComRef-MainValue>1.0</ComRef-MainValue>
            <ComRef-LowerBound>1.0</ComRef-LowerBound>
            <ComRef-UpperBound>1.0</ComRef-UpperBound>
        </Component>
    </Components>
    <Compositions/>
</XML>
