<?xml version="1.0" encoding="UTF-8" standalone="no"?>
<XML>
    <Flows/>
    <ProcessModules/>
    <FlowValueMapGroups/>
    <ProductSystems/>
    <ImpactCategories>
        <ImpactCategory>
            <Category>Klimawandel</Category>
            <Indicator>kg CO_(2)-Äq.</Indicator>
        </ImpactCategory>
        <ImpactCategory>
            <Category>Abbau der stratosphärischen Ozonschicht </Category>
            <Indicator>kg CFC11-Äq.</Indicator>
        </ImpactCategory>
        <ImpactCategory>
            <Category>Versauerung</Category>
            <Indicator>kg SO_(2)-Äq.</Indicator>
        </ImpactCategory>
        <ImpactCategory>
            <Category>Eutrophierung </Category>
            <Indicator>kg PO_(4)^(3)-Äq.</Indicator>
        </ImpactCategory>
        <ImpactCategory>
            <Category>Bildung von troposphärischen Ozon</Category>
            <Indicator>kg Ethen-Äq.</Indicator>
        </ImpactCategory>
        <ImpactCategory>
            <Category>Verknappung von abiotischen Ressourcen(Elemente) </Category>
            <Indicator>kg Sb-Äq.</Indicator>
        </ImpactCategory>
        <ImpactCategory>
            <Category>Verknappung von fossiler Ressourcen</Category>
            <Indicator>MJ</Indicator>
        </ImpactCategory>
    </ImpactCategories>
    <CFactors/>
    <LCIAMethods/>
    <ProductDeclarations>
        <ProductDeclaration>
            <PD-Name>compact reader 91 10 (compact reader 91 10)(en)</PD-Name>
            <PD-Unit>Items</PD-Unit>
            <ImpactValuesVector>
                <IVV-Entry>
                    <ImpactCategorie-Name>Klimawandel</ImpactCategorie-Name>
                    <ICV-MainValue>145.86</ICV-MainValue>
                    <ICV-UpperBound>145.86</ICV-UpperBound>
                    <ICV-LowerBound>145.86</ICV-LowerBound>
                </IVV-Entry>
                <IVV-Entry>
                    <ImpactCategorie-Name>Abbau der stratosphärischen Ozonschicht </ImpactCategorie-Name>
                    <ICV-MainValue>0</ICV-MainValue>
                    <ICV-UpperBound>0</ICV-UpperBound>
                    <ICV-LowerBound>0</ICV-LowerBound>
                </IVV-Entry>
                <IVV-Entry>
                    <ImpactCategorie-Name>Versauerung</ImpactCategorie-Name>
                    <ICV-MainValue>0.42</ICV-MainValue>
                    <ICV-UpperBound>0.42</ICV-UpperBound>
                    <ICV-LowerBound>0.42</ICV-LowerBound>
                </IVV-Entry>
                <IVV-Entry>
                    <ImpactCategorie-Name>Eutrophierung </ImpactCategorie-Name>
                    <ICV-MainValue>0.04</ICV-MainValue>
                    <ICV-UpperBound>0.04</ICV-UpperBound>
                    <ICV-LowerBound>0.04</ICV-LowerBound>
                </IVV-Entry>
                <IVV-Entry>
                    <ImpactCategorie-Name>Bildung von troposphärischen Ozon</ImpactCategorie-Name>
                    <ICV-MainValue>0.03</ICV-MainValue>
                    <ICV-UpperBound>0.03</ICV-UpperBound>
                    <ICV-LowerBound>0.03</ICV-LowerBound>
                </IVV-Entry>
                <IVV-Entry>
                    <ImpactCategorie-Name>Verknappung von abiotischen Ressourcen(Elemente) </ImpactCategorie-Name>
                    <ICV-MainValue>-0</ICV-MainValue>
                    <ICV-UpperBound>-0</ICV-UpperBound>
                    <ICV-LowerBound>-0</ICV-LowerBound>
                </IVV-Entry>
                <IVV-Entry>
                    <ImpactCategorie-Name>Verknappung von fossiler Ressourcen</ImpactCategorie-Name>
                    <ICV-MainValue>1568.75</ICV-MainValue>
                    <ICV-UpperBound>1568.75</ICV-UpperBound>
                    <ICV-LowerBound>1568.75</ICV-LowerBound>
                </IVV-Entry>
            </ImpactValuesVector>
        </ProductDeclaration>
    </ProductDeclarations>
    <ImpactValueMapGroups/>
    <Components>
        <Component>
            <Component-Name>Komponent_Online Access Control Devices - Compact Readers(en)</Component-Name>
            <Component-Unit>Items</Component-Unit>
            <Component-Reference>compact reader 91 10 (compact reader 91 10)(en)</Component-Reference>
            <ComRef-MainValue>1</ComRef-MainValue>
            <ComRef-LowerBound>1</ComRef-LowerBound>
            <ComRef-UpperBound>1</ComRef-UpperBound>
        </Component>
    </Components>
    <Compositions/>
</XML>
